kshift/__init__.py
kshift/conf.py
kshift/defaults.yml
kshift/main.py
kshift/theme.py
kshift/utils.py
kshift/templates/template.service
kshift/templates/template.timer
kshift-1.2.4.dist-info/METADATA
kshift-1.2.4.dist-info/WHEEL
kshift-1.2.4.dist-info/entry_points.txt
kshift-1.2.4.dist-info/licenses/LICENSE
kshift-1.2.4.dist-info/RECORD
