Metadata-Version: 2.4
Name: kshift
Version: 1.2.4
Summary: KDE Theme Shift
Project-URL: Homepage, https://github.com/justjokiing/kshift
Author-email: Seth Mackert <seth.mackert@fastsycamore.com>
License: GPL-3.0-or-later
License-File: LICENSE
Keywords: KDE,KDE Plasma,Linux,Plasma,automation,color scheme,cron replacement,desktop customization,desktop environment,icon theme,script,sunrise sunset,systemd,theme,theme switching,timers,wallpaper
Classifier: Development Status :: 5 - Production/Stable
Classifier: Environment :: Console
Classifier: Environment :: X11 Applications :: KDE
Classifier: Intended Audience :: Developers
Classifier: Intended Audience :: End Users/Desktop
Classifier: License :: OSI Approved :: GNU General Public License v3 or later (GPLv3+)
Classifier: Operating System :: POSIX :: Linux
Classifier: Programming Language :: Python
Classifier: Topic :: Desktop Environment :: K Desktop Environment (KDE)
Classifier: Topic :: Desktop Environment :: K Desktop Environment (KDE) :: Themes
Classifier: Topic :: Utilities
Requires-Dist: click
Requires-Dist: colorama
Requires-Dist: pydantic
Requires-Dist: pyyaml
Requires-Dist: requests
